LICENSE
MANIFEST.in
README.rst
requirements.txt
setup.cfg
setup.py
melomaniac/__init__.py
melomaniac/app.py
melomaniac/manager.py
melomaniac/version.py
melomaniac.egg-info/PKG-INFO
melomaniac.egg-info/SOURCES.txt
melomaniac.egg-info/dependency_links.txt
melomaniac.egg-info/entry_points.txt
melomaniac.egg-info/requires.txt
melomaniac.egg-info/top_level.txt
melomaniac/commands/__init__.py
melomaniac/commands/cache_clear.py
melomaniac/commands/listen.py
melomaniac/contracts/__init__.py
melomaniac/contracts/backend.py
melomaniac/gmusic/__init__.py
melomaniac/gmusic/backend.py
melomaniac/gmusic/library.py
melomaniac/gmusic/test_library.py
melomaniac/gmusic/ui.py
melomaniac/player/__init__.py
melomaniac/player/album.py
melomaniac/player/artist.py
melomaniac/player/item.py
melomaniac/player/library.py
melomaniac/player/list.py
melomaniac/player/player.py
melomaniac/player/playlist.py
melomaniac/player/track.py
melomaniac/soundcloud/__init__.py
melomaniac/soundcloud/backend.py
melomaniac/soundcloud/client.py
melomaniac/soundcloud/library.py
melomaniac/soundcloud/ui.py
melomaniac/ui/__init__.py
melomaniac/ui/canvas.py
melomaniac/ui/colors.py
melomaniac/ui/controller.py
melomaniac/ui/ui.py
melomaniac/ui/view.py