Metadata-Version: 1.1
Name: melomaniac
Version: 0.1.1
Summary: Listen to your Google Play Music/Soundcloud library from your terminal.
Home-page: https://github.com/sdispater/melomaniac
Author: Sébastien Eustace
Author-email: sebastien@eustace.io
License: MIT
Download-URL: https://github.com/sdispater/melomaniac/archive/0.1.1.tar.gz
Platform: UNKNOWN
Classifier: Intended Audience :: Developers
Classifier: Operating System :: OS Independent
Classifier: Programming Language :: Python
Classifier: Topic :: Software Development :: Libraries :: Python Modules
